[{"product": "Jam", "meta data": "Quantity: 20", "": "Price: $9"}, {"product": "Cheese", "meta data": "Quantity: 18", "": "Price: $17"}, {"product": "Milk", "meta data": "Quantity: 2", "": "Price: $1"}, {"product": "Bread", "meta data": "Quantity: 102", "": "Price: $5"}, {"product": "Free Range Eggs", "meta data": "Quantity: 12", "": "Price: $3.00"}, {"product": "Apples", "meta data": "Quantity: 32", "": "Price: $1"}, {"product": "Oranges", "meta data": "Quantity: 72", "": "Price: $4.5"}, {"product": "Butter", "meta data": "Quantity: 10", "": "Price: $4"}, {"product": "Flour", "meta data": "Quantity: 5", "": "Price: $0.50"}, {"product": "Custard", "meta data": "Quantity: 10", "": "Price: $10"}, {"product": "Jam", "meta data": "Quantity: 19", "": "Price: $7"}, {"product": "Fish", "meta data": "Quantity: 7", "": "Price: $6"}, {"product": "Yoghurt", "meta data": "Quantity: 5", "": "Price: $3"}, {"product": "Pie", "meta data": "Quantity: 2", "": "Price: $4"}, {"product": "Bottled Water", "meta data": "Quantity: 11", "": "Price: $19"}, {"product": "Pizza", "meta data": "Quantity: 8", "": "Price: $3"}, {"product": "Ice Cubes", "meta data": "Quantity: 400", "": "Price: $0.50"}, {"product": "Tea", "meta data": "Quantity: 20", "": "Price: $1"}, {"product": "Coffee", "meta data": "Quantity: 10", "": "Price: $5"}]